flowlog_pprint/__init__.py
flowlog_pprint/__main__.py
flowlog_pprint/flowlog_pprint.py
flowlog_pprint-0.0.4.dist-info/LICENSE
flowlog_pprint-0.0.4.dist-info/METADATA
flowlog_pprint-0.0.4.dist-info/WHEEL
flowlog_pprint-0.0.4.dist-info/entry_points.txt
flowlog_pprint-0.0.4.dist-info/top_level.txt
flowlog_pprint-0.0.4.dist-info/RECORD
