Metadata-Version: 2.1
Name: flowlog-pprint
Version: 0.0.4
Summary: UNKNOWN
Home-page: https://github.com/d-karlss/flowlog-pprint
License: UNKNOWN
Platform: UNKNOWN
Classifier: Programming Language :: Python :: 3
Classifier: License :: OSI Approved :: MIT License
Classifier: Operating System :: OS Independent
Requires-Python: >=3.5.0
Requires-Dist: colorama
